{"id":20987,"org_id":23943,"name":"Freedom Online","aka":"Freedom Online","name_long":"","website":"http://www.freedomonlineltd.com","social_media":[{"service":"website","identifier":"http://www.freedomonlineltd.com"}],"asn":139675,"looking_glass":"","route_server":"","irr_as_set":"AS-FREEDOM-AS-AP","info_type":"Cable/DSL/ISP","info_types":["Cable/DSL/ISP"],"info_prefixes4":2,"info_prefixes6":10,"info_traffic":"5-10Gbps","info_ratio":"Mostly Inbound","info_scope":"Asia Pacific","info_unicast":true,"info_multicast":false,"info_ipv6":true,"info_never_via_route_servers":false,"ix_count":0,"fac_count":0,"notes":"Freedom Online(ASN 139675)  is one of the best internet Service Provider of Narayanganj district in Bangladesh. We have a network connect to rural areas thus we have the largest customer base. We want to peering with every contents providers to improve our customers experience.","netixlan_updated":null,"netfac_updated":null,"poc_updated":"2020-03-30T19:20:46Z","policy_url":"http://www.freedomonlineltd.com","policy_general":"Open","policy_locations":"Not Required","policy_ratio":false,"policy_contracts":"Not Required","allow_ixp_update":false,"status_dashboard":null,"rir_status":"ok","rir_status_updated":"2024-06-26T04:47:55Z","logo":null,"created":"2019-09-26T20:04:40Z","updated":"2022-07-27T05:35:38Z","status":"ok"}