{"id":12067,"org_id":15792,"name":"Connexity","aka":"Shopzilla, Inc","name_long":"","website":"http://www.connexity.com","social_media":[{"service":"website","identifier":"http://www.connexity.com"}],"asn":14332,"looking_glass":"","route_server":"","irr_as_set":"AS-CONNEXITY","info_type":"Content","info_types":["Content"],"info_prefixes4":16,"info_prefixes6":0,"info_traffic":"","info_ratio":"Not Disclosed","info_scope":"Not Disclosed","info_unicast":true,"info_multicast":false,"info_ipv6":false,"info_never_via_route_servers":false,"ix_count":0,"fac_count":0,"notes":"","netixlan_updated":null,"netfac_updated":"2025-03-10T02:25:46Z","poc_updated":null,"policy_url":"","policy_general":"Open","policy_locations":"Not Required","policy_ratio":false,"policy_contracts":"Not Required","allow_ixp_update":false,"status_dashboard":"","rir_status":"ok","rir_status_updated":"2024-06-26T04:47:55Z","logo":null,"created":"2016-12-17T21:47:53Z","updated":"2025-03-10T02:25:49Z","status":"ok"}