{"id":29322,"org_id":31801,"name":"Padmesh Broadband","aka":"","name_long":"","website":"","social_media":[],"asn":149261,"looking_glass":"","route_server":"","irr_as_set":"","info_type":"","info_types":[],"info_prefixes4":10,"info_prefixes6":10,"info_traffic":"1-5Gbps","info_ratio":"Mostly Inbound","info_scope":"Not Disclosed","info_unicast":false,"info_multicast":false,"info_ipv6":false,"info_never_via_route_servers":false,"ix_count":1,"fac_count":0,"notes":"","netixlan_updated":"2022-10-20T10:37:53Z","netfac_updated":null,"poc_updated":"2022-06-16T06:55:01Z","policy_url":"","policy_general":"Open","policy_locations":"Not Required","policy_ratio":false,"policy_contracts":"Not Required","allow_ixp_update":false,"status_dashboard":"","rir_status":"ok","rir_status_updated":"2024-06-26T04:47:55Z","logo":null,"created":"2022-02-23T07:58:20Z","updated":"2022-10-26T05:17:48Z","status":"ok"}