{"id":42240,"org_id":43997,"name":"FAT-AS-AP","aka":"","name_long":"FAT FAT LA COMPANY","website":"https://fatfat.la","social_media":[{"service":"website","identifier":"https://fatfat.la"}],"asn":150338,"looking_glass":"","route_server":"","irr_as_set":"APNIC::AS150338","info_type":"Enterprise","info_types":["Enterprise"],"info_prefixes4":0,"info_prefixes6":1,"info_traffic":"","info_ratio":"Not Disclosed","info_scope":"Asia Pacific","info_unicast":false,"info_multicast":false,"info_ipv6":true,"info_never_via_route_servers":false,"ix_count":0,"fac_count":0,"notes":"","netixlan_updated":null,"netfac_updated":null,"poc_updated":null,"policy_url":"","policy_general":"Open","policy_locations":"Not Required","policy_ratio":false,"policy_contracts":"Not Required","allow_ixp_update":false,"status_dashboard":"","rir_status":"ok","rir_status_updated":"2026-04-25T22:55:27Z","logo":null,"created":"2026-04-25T13:05:35Z","updated":"2026-04-25T13:10:50Z","status":"ok"}