{"id":32194,"org_id":34444,"name":"Server Galactic","aka":"Server Galactic Limited","name_long":"","website":"https://www.servergalactic.asia","social_media":[{"service":"website","identifier":"https://www.servergalactic.asia"}],"asn":150423,"looking_glass":"","route_server":"","irr_as_set":"AS150423:AS-PEERS","info_type":"Cable/DSL/ISP","info_types":["Cable/DSL/ISP"],"info_prefixes4":2,"info_prefixes6":2,"info_traffic":"5-10Gbps","info_ratio":"Mostly Outbound","info_scope":"Asia Pacific","info_unicast":true,"info_multicast":false,"info_ipv6":true,"info_never_via_route_servers":false,"ix_count":1,"fac_count":3,"notes":"","netixlan_updated":"2025-05-14T10:00:57Z","netfac_updated":"2024-05-06T06:46:26Z","poc_updated":"2023-04-19T15:54:45Z","policy_url":"","policy_general":"Open","policy_locations":"Not Required","policy_ratio":false,"policy_contracts":"Not Required","allow_ixp_update":false,"status_dashboard":"","rir_status":"ok","rir_status_updated":"2024-06-26T04:47:55Z","logo":null,"created":"2023-02-04T02:10:21Z","updated":"2025-09-08T08:59:38Z","status":"ok"}