{"id":42065,"org_id":43815,"name":"Bintang Teknologi Sejahtera","aka":"","name_long":"PT Bintang Teknologi Sejahtera","website":"http://Binteks.id","social_media":[{"service":"website","identifier":"http://Binteks.id"}],"asn":150468,"looking_glass":"","route_server":"","irr_as_set":"IDNIC::AS150468:AS-BINTANG","info_type":"Cable/DSL/ISP","info_types":["Cable/DSL/ISP"],"info_prefixes4":1,"info_prefixes6":null,"info_traffic":"","info_ratio":"Not Disclosed","info_scope":"Not Disclosed","info_unicast":true,"info_multicast":false,"info_ipv6":false,"info_never_via_route_servers":false,"ix_count":1,"fac_count":1,"notes":"","netixlan_updated":"2026-04-10T17:19:50Z","netfac_updated":"2026-04-13T21:21:56Z","poc_updated":"2026-04-10T09:04:57Z","policy_url":"http://binteks.id","policy_general":"Open","policy_locations":"Not Required","policy_ratio":false,"policy_contracts":"Not Required","allow_ixp_update":true,"status_dashboard":"","rir_status":"ok","rir_status_updated":"2026-04-08T22:55:27Z","logo":null,"created":"2026-04-08T07:31:42Z","updated":"2026-04-16T15:42:12Z","status":"ok"}