{"id":39779,"org_id":41535,"name":"Shankara Kalandra Jaya","aka":"ABIFIBER","name_long":"PT Shankara Kalandra Jaya","website":"https://abifiber.net","social_media":[{"service":"website","identifier":"https://abifiber.net"}],"asn":150690,"looking_glass":"","route_server":"","irr_as_set":"AS150690","info_type":"Cable/DSL/ISP","info_types":["Cable/DSL/ISP"],"info_prefixes4":1,"info_prefixes6":1,"info_traffic":"1-5Gbps","info_ratio":"Heavy Inbound","info_scope":"Not Disclosed","info_unicast":true,"info_multicast":false,"info_ipv6":false,"info_never_via_route_servers":false,"ix_count":1,"fac_count":0,"notes":"","netixlan_updated":"2026-04-04T16:40:26Z","netfac_updated":null,"poc_updated":"2025-12-12T18:24:49Z","policy_url":"","policy_general":"Open","policy_locations":"Not Required","policy_ratio":false,"policy_contracts":"Not Required","allow_ixp_update":true,"status_dashboard":null,"rir_status":"ok","rir_status_updated":"2025-07-12T22:55:07Z","logo":null,"created":"2025-07-11T16:54:17Z","updated":"2026-04-04T16:40:27Z","status":"ok"}