{"id":39278,"org_id":41036,"name":"SIGMA","aka":"SIGMA","name_long":"PT Sigma Data Nusa","website":"http://www.sigmadata.id","social_media":[{"service":"website","identifier":"http://www.sigmadata.id"}],"asn":153155,"looking_glass":"","route_server":"","irr_as_set":"","info_type":"","info_types":[],"info_prefixes4":23,"info_prefixes6":null,"info_traffic":"","info_ratio":"Not Disclosed","info_scope":"Not Disclosed","info_unicast":true,"info_multicast":true,"info_ipv6":false,"info_never_via_route_servers":false,"ix_count":3,"fac_count":1,"notes":"","netixlan_updated":"2026-03-26T15:46:31Z","netfac_updated":"2025-11-24T12:52:56Z","poc_updated":"2025-07-03T15:57:45Z","policy_url":"","policy_general":"Open","policy_locations":"Not Required","policy_ratio":false,"policy_contracts":"Not Required","allow_ixp_update":false,"status_dashboard":"","rir_status":"ok","rir_status_updated":"2025-06-26T22:55:06Z","logo":null,"created":"2025-05-11T23:23:41Z","updated":"2026-03-25T08:38:01Z","status":"ok"}