{"id":23232,"org_id":26042,"name":"Telefonica Empresas Network","aka":"Movistar Empresas","name_long":"","website":"https://ww2.movistar.cl/empresas/","social_media":[{"service":"website","identifier":"https://ww2.movistar.cl/empresas/"}],"asn":15311,"looking_glass":"","route_server":"","irr_as_set":"","info_type":"","info_types":[],"info_prefixes4":80,"info_prefixes6":4,"info_traffic":"20-50Gbps","info_ratio":"Mostly Inbound","info_scope":"Regional","info_unicast":true,"info_multicast":false,"info_ipv6":true,"info_never_via_route_servers":false,"ix_count":0,"fac_count":0,"notes":"","netixlan_updated":null,"netfac_updated":null,"poc_updated":"2020-05-14T00:56:52Z","policy_url":"","policy_general":"Open","policy_locations":"Not Required","policy_ratio":false,"policy_contracts":"Not Required","allow_ixp_update":false,"status_dashboard":null,"rir_status":"ok","rir_status_updated":"2024-06-26T04:47:55Z","logo":null,"created":"2020-05-12T01:06:10Z","updated":"2022-07-27T05:33:39Z","status":"ok"}