{"id":39527,"org_id":41291,"name":"Grizylnet Indo Multimedia","aka":"","name_long":"PT Grizylnet Indo Multimedia","website":"https://grizylnetindomultimedia.id/","social_media":[{"service":"website","identifier":"https://grizylnetindomultimedia.id/"}],"asn":153553,"looking_glass":"","route_server":"","irr_as_set":"","info_type":"Cable/DSL/ISP","info_types":["Cable/DSL/ISP"],"info_prefixes4":2,"info_prefixes6":1,"info_traffic":"100-1000Mbps","info_ratio":"","info_scope":"Not Disclosed","info_unicast":true,"info_multicast":false,"info_ipv6":true,"info_never_via_route_servers":false,"ix_count":0,"fac_count":1,"notes":"","netixlan_updated":null,"netfac_updated":"2025-06-08T12:39:07Z","poc_updated":"2025-06-08T12:38:47Z","policy_url":"https://www.peeringdb.com/net/39527","policy_general":"Open","policy_locations":"Not Required","policy_ratio":false,"policy_contracts":"Not Required","allow_ixp_update":false,"status_dashboard":null,"rir_status":"ok","rir_status_updated":"2025-06-08T22:55:09Z","logo":null,"created":"2025-06-08T12:30:46Z","updated":"2026-04-04T16:31:26Z","status":"ok"}