{"id":20637,"org_id":1790,"name":"XLSmart AS17885","aka":"XL, XLNET, EXCELCOM, XL AXIATA","name_long":"","website":"https://www.xlsmart.co.id","social_media":[{"service":"website","identifier":"https://www.xlsmart.co.id"}],"asn":17885,"looking_glass":"","route_server":"","irr_as_set":"AS17885:AS-JKTXLNET","info_type":"NSP","info_types":["NSP"],"info_prefixes4":5000,"info_prefixes6":500,"info_traffic":"500-1000Gbps","info_ratio":"Not Disclosed","info_scope":"Regional","info_unicast":true,"info_multicast":false,"info_ipv6":true,"info_never_via_route_servers":false,"ix_count":2,"fac_count":11,"notes":"","netixlan_updated":"2024-10-15T00:25:21Z","netfac_updated":"2023-01-09T07:05:56Z","poc_updated":"2025-10-23T08:10:22Z","policy_url":"","policy_general":"Selective","policy_locations":"Not Required","policy_ratio":false,"policy_contracts":"Not Required","allow_ixp_update":false,"status_dashboard":"","rir_status":"ok","rir_status_updated":"2024-06-26T04:47:55Z","logo":null,"created":"2019-08-18T14:40:24Z","updated":"2025-10-23T10:18:51Z","status":"ok"}