{"id":14907,"org_id":1238,"name":"NTT DATA, Broadband, South Africa","aka":"NTT DATA Broadband","name_long":"","website":"https://services.global.ntt/en-us/","social_media":[{"service":"website","identifier":"https://services.global.ntt/en-us/"}],"asn":20011,"looking_glass":"https://lg.as20011.net/","route_server":"","irr_as_set":"RADB::AS-IS2","info_type":"Cable/DSL/ISP","info_types":["Cable/DSL/ISP"],"info_prefixes4":2500,"info_prefixes6":4,"info_traffic":"500-1000Gbps","info_ratio":"Not Disclosed","info_scope":"Africa","info_unicast":true,"info_multicast":false,"info_ipv6":true,"info_never_via_route_servers":false,"ix_count":6,"fac_count":0,"notes":"","netixlan_updated":"2025-05-09T08:43:10Z","netfac_updated":null,"poc_updated":"2024-04-02T08:53:03Z","policy_url":"https://mirror.dimensiondata.com/mirror/dimensiondata.com/peering.pdf","policy_general":"Selective","policy_locations":"Preferred","policy_ratio":false,"policy_contracts":"Not Required","allow_ixp_update":false,"status_dashboard":"","rir_status":"ok","rir_status_updated":"2024-06-26T04:47:55Z","logo":null,"created":"2017-10-12T14:34:37Z","updated":"2025-07-17T07:11:01Z","status":"ok"}