{"id":41738,"org_id":43436,"name":"Lucy Hochkamp #41738","aka":"XynoSystems","name_long":"","website":"https://xyno.systems","social_media":[{"service":"mastodon","identifier":"https://mastodon.catgirl.cloud/@xyno"},{"service":"website","identifier":"https://xyno.systems"}],"asn":200287,"looking_glass":"","route_server":"","irr_as_set":"","info_type":"","info_types":[],"info_prefixes4":0,"info_prefixes6":16,"info_traffic":"0-20Mbps","info_ratio":"Not Disclosed","info_scope":"Not Disclosed","info_unicast":false,"info_multicast":false,"info_ipv6":true,"info_never_via_route_servers":false,"ix_count":0,"fac_count":0,"notes":"","netixlan_updated":null,"netfac_updated":null,"poc_updated":"2026-03-23T09:00:41Z","policy_url":"","policy_general":"Open","policy_locations":"Not Required","policy_ratio":false,"policy_contracts":"Not Required","allow_ixp_update":true,"status_dashboard":null,"rir_status":"ok","rir_status_updated":"2026-02-26T08:01:00Z","logo":null,"created":"2026-02-26T08:01:01Z","updated":"2026-03-23T09:00:42Z","status":"deleted"}