{"id":4860,"org_id":7019,"name":"UAB \"CGATES\"","aka":"CGATES-LT","name_long":"","website":"http://www.cgates.lt","social_media":[{"service":"website","identifier":"http://www.cgates.lt"}],"asn":21412,"looking_glass":"","route_server":"","irr_as_set":"AS-21412","info_type":"Cable/DSL/ISP","info_types":["Cable/DSL/ISP"],"info_prefixes4":100,"info_prefixes6":10,"info_traffic":"","info_ratio":"Mostly Inbound","info_scope":"Regional","info_unicast":true,"info_multicast":true,"info_ipv6":true,"info_never_via_route_servers":false,"ix_count":4,"fac_count":0,"notes":"","netixlan_updated":"2026-01-30T09:49:38Z","netfac_updated":null,"poc_updated":"2021-01-25T08:23:48Z","policy_url":"","policy_general":"Open","policy_locations":"Not Required","policy_ratio":false,"policy_contracts":"Not Required","allow_ixp_update":false,"status_dashboard":"","rir_status":"ok","rir_status_updated":"2024-06-26T04:47:55Z","logo":null,"created":"2012-07-03T02:02:06Z","updated":"2025-02-28T12:07:38Z","status":"ok"}