{"id":17755,"org_id":425,"name":"CTGNet","aka":"CTGNet","name_long":"","website":"https://www.chinatelecomglobal.com/","social_media":[{"service":"website","identifier":"https://www.chinatelecomglobal.com/"}],"asn":23764,"looking_glass":"https://ipms.chinatelecomglobal.com/public/lookglass/lookglassDisclaimer.html","route_server":"","irr_as_set":"AS-CTGNET","info_type":"NSP","info_types":["NSP"],"info_prefixes4":50000,"info_prefixes6":5000,"info_traffic":"","info_ratio":"Balanced","info_scope":"Global","info_unicast":true,"info_multicast":false,"info_ipv6":true,"info_never_via_route_servers":false,"ix_count":40,"fac_count":23,"notes":"","netixlan_updated":"2026-01-28T06:09:02Z","netfac_updated":"2024-08-27T02:05:51Z","poc_updated":"2023-03-16T03:22:07Z","policy_url":"","policy_general":"Selective","policy_locations":"Preferred","policy_ratio":true,"policy_contracts":"Private Only","allow_ixp_update":false,"status_dashboard":"","rir_status":"ok","rir_status_updated":"2024-06-26T04:47:55Z","logo":null,"created":"2018-09-15T09:43:06Z","updated":"2026-01-28T06:09:02Z","status":"ok"}