{"id":10851,"org_id":14698,"name":"Fonte Informática","aka":"","name_long":"","website":"http://www.fontetelecom.com.br/","social_media":[{"service":"website","identifier":"http://www.fontetelecom.com.br/"}],"asn":263346,"looking_glass":"","route_server":"","irr_as_set":"","info_type":"Cable/DSL/ISP","info_types":["Cable/DSL/ISP"],"info_prefixes4":200,"info_prefixes6":200,"info_traffic":"100-200Gbps","info_ratio":"Balanced","info_scope":"Regional","info_unicast":true,"info_multicast":true,"info_ipv6":true,"info_never_via_route_servers":false,"ix_count":3,"fac_count":2,"notes":"","netixlan_updated":"2024-10-16T20:18:08Z","netfac_updated":"2023-05-19T12:53:54Z","poc_updated":"2024-10-03T14:50:08Z","policy_url":"https://registro.br/tecnologia/ferramentas/whois/?search=%20263346","policy_general":"Open","policy_locations":"Not Required","policy_ratio":false,"policy_contracts":"Not Required","allow_ixp_update":false,"status_dashboard":"","rir_status":"ok","rir_status_updated":"2024-06-26T04:47:55Z","logo":null,"created":"2016-08-01T14:32:29Z","updated":"2024-10-03T14:50:11Z","status":"ok"}