{"id":18374,"org_id":21490,"name":"TELEALFACOM","aka":"ALFANET","name_long":"","website":"http://www.alfanet.ec","social_media":[{"service":"tiktok","identifier":"alfanetececuador"},{"service":"youtube","identifier":"AlfanetEcuador"},{"service":"instagram","identifier":"alfanetececuador"},{"service":"linkedin","identifier":"alfanetececuador"},{"service":"facebook","identifier":"alfanetececuador"},{"service":"website","identifier":"http://www.alfanet.ec"}],"asn":264825,"looking_glass":"","route_server":"","irr_as_set":"AS264825:AS-TELEALFACOM","info_type":"Cable/DSL/ISP","info_types":["Cable/DSL/ISP"],"info_prefixes4":5,"info_prefixes6":1,"info_traffic":"10-20Gbps","info_ratio":"Mostly Inbound","info_scope":"South America","info_unicast":true,"info_multicast":false,"info_ipv6":true,"info_never_via_route_servers":false,"ix_count":2,"fac_count":2,"notes":"","netixlan_updated":"2026-02-01T04:16:34Z","netfac_updated":"2025-09-01T16:19:49Z","poc_updated":"2026-02-12T13:47:37Z","policy_url":"","policy_general":"Open","policy_locations":"Not Required","policy_ratio":false,"policy_contracts":"Not Required","allow_ixp_update":false,"status_dashboard":"","rir_status":"ok","rir_status_updated":"2024-06-26T04:47:55Z","logo":null,"created":"2018-11-20T18:34:43Z","updated":"2026-02-12T13:47:38Z","status":"ok"}