{"id":17945,"org_id":21092,"name":"CLICK & NAVEGUE TELECOMUNICAÇÕES","aka":"Click & Navegue","name_long":"Click & Navegue","website":"https://www.clicknavegue.com.br","social_media":[{"service":"website","identifier":"https://www.clicknavegue.com.br"}],"asn":268459,"looking_glass":"","route_server":"","irr_as_set":"AS268459","info_type":"Cable/DSL/ISP","info_types":["Cable/DSL/ISP"],"info_prefixes4":7,"info_prefixes6":16,"info_traffic":"1-5Gbps","info_ratio":"Heavy Outbound","info_scope":"South America","info_unicast":true,"info_multicast":true,"info_ipv6":true,"info_never_via_route_servers":false,"ix_count":1,"fac_count":0,"notes":"","netixlan_updated":"2021-07-08T20:40:45Z","netfac_updated":null,"poc_updated":"2019-10-25T19:37:01Z","policy_url":"","policy_general":"Open","policy_locations":"Not Required","policy_ratio":false,"policy_contracts":"Not Required","allow_ixp_update":false,"status_dashboard":null,"rir_status":"ok","rir_status_updated":"2024-06-26T04:47:55Z","logo":null,"created":"2018-10-04T21:20:40Z","updated":"2022-07-27T05:36:46Z","status":"ok"}