{"id":29052,"org_id":31523,"name":"KM TECHNOLOGY","aka":"KM NET - La Red que si Funciona","name_long":"KM TECHNOLOGY, C.A.","website":"http://kmnet.com.ve","social_media":[{"service":"website","identifier":"http://kmnet.com.ve"}],"asn":272018,"looking_glass":"http://lg.kmnet.com.ve/","route_server":"http://irr.kmnet.com.net/cgi-bin/lg.cgi","irr_as_set":"AS272018:AS-CUSTOMERS","info_type":"Cable/DSL/ISP","info_types":["Cable/DSL/ISP"],"info_prefixes4":10000,"info_prefixes6":500,"info_traffic":"50-100Gbps","info_ratio":"Balanced","info_scope":"Regional","info_unicast":true,"info_multicast":true,"info_ipv6":true,"info_never_via_route_servers":true,"ix_count":0,"fac_count":0,"notes":"","netixlan_updated":"2025-06-25T16:15:26Z","netfac_updated":null,"poc_updated":"2025-06-25T16:16:20Z","policy_url":"","policy_general":"Open","policy_locations":"Not Required","policy_ratio":false,"policy_contracts":"Not Required","allow_ixp_update":false,"status_dashboard":"","rir_status":"ok","rir_status_updated":"2024-06-26T04:47:55Z","logo":null,"created":"2022-01-17T20:28:19Z","updated":"2025-06-25T16:16:56Z","status":"ok"}