{"id":41955,"org_id":43707,"name":"ORIONNET TELECOM TECNOLOGIA E SERVIÇOS","aka":"ÓRION NET","name_long":"ORIONNET TELECOM TECNOLOGIA E SERVIÇOS","website":"https://orionfibra.net.br/","social_media":[{"service":"instagram","identifier":"orionnet.telecom"},{"service":"website","identifier":"https://orionfibra.net.br/"}],"asn":273333,"looking_glass":"","route_server":"","irr_as_set":"AS273333:AS-ALL","info_type":"NSP","info_types":["Cable/DSL/ISP","NSP","Network Services"],"info_prefixes4":900,"info_prefixes6":900,"info_traffic":"5-10Gbps","info_ratio":"Balanced","info_scope":"Regional","info_unicast":true,"info_multicast":false,"info_ipv6":true,"info_never_via_route_servers":false,"ix_count":1,"fac_count":0,"notes":"","netixlan_updated":"2026-03-30T22:02:26Z","netfac_updated":null,"poc_updated":"2026-03-28T14:21:04Z","policy_url":"https://www.iptp.net/","policy_general":"Open","policy_locations":"Not Required","policy_ratio":false,"policy_contracts":"Required","allow_ixp_update":false,"status_dashboard":null,"rir_status":"ok","rir_status_updated":"2026-03-26T22:55:24Z","logo":"https://peeringdb-media-prod.s3.amazonaws.com/media/logos_user_supplied/network-41955-d3ffaaca.jpg","created":"2026-03-26T01:20:16Z","updated":"2026-03-30T22:02:26Z","status":"ok"}