{"id":36241,"org_id":38235,"name":"NOW FIBRA PROVEDOR DE INTERNET","aka":"","name_long":"NOW FIBRA PROVEDOR DE INTERNET","website":"https://www.nowfibra.com.br","social_media":[{"service":"website","identifier":"https://www.nowfibra.com.br"}],"asn":273480,"looking_glass":"","route_server":"","irr_as_set":"AS273480:AS-ALL","info_type":"Cable/DSL/ISP","info_types":["Cable/DSL/ISP"],"info_prefixes4":22,"info_prefixes6":32,"info_traffic":"","info_ratio":"Not Disclosed","info_scope":"Regional","info_unicast":false,"info_multicast":false,"info_ipv6":false,"info_never_via_route_servers":false,"ix_count":1,"fac_count":0,"notes":"","netixlan_updated":"2026-02-22T13:35:35Z","netfac_updated":null,"poc_updated":"2026-03-20T09:09:36Z","policy_url":"","policy_general":"Selective","policy_locations":"Not Required","policy_ratio":false,"policy_contracts":"Not Required","allow_ixp_update":false,"status_dashboard":"","rir_status":"ok","rir_status_updated":"2024-06-26T04:47:55Z","logo":null,"created":"2024-05-16T10:24:54Z","updated":"2026-03-20T09:09:20Z","status":"ok"}