{"id":33690,"org_id":35871,"name":"Vinnytsia National Technical University","aka":"VNTU","name_long":"","website":"https://vntu.edu.ua/","social_media":[{"service":"website","identifier":"https://vntu.edu.ua/"}],"asn":29574,"looking_glass":"","route_server":"","irr_as_set":"AS-VNTU","info_type":"Educational/Research","info_types":["Educational/Research"],"info_prefixes4":4,"info_prefixes6":0,"info_traffic":"","info_ratio":"Not Disclosed","info_scope":"Not Disclosed","info_unicast":false,"info_multicast":false,"info_ipv6":false,"info_never_via_route_servers":false,"ix_count":0,"fac_count":0,"notes":"","netixlan_updated":null,"netfac_updated":null,"poc_updated":"2023-07-23T10:59:12Z","policy_url":"","policy_general":"No","policy_locations":"Not Required","policy_ratio":false,"policy_contracts":"Not Required","allow_ixp_update":false,"status_dashboard":"","rir_status":"ok","rir_status_updated":"2024-06-26T04:47:55Z","logo":null,"created":"2023-07-23T10:16:05Z","updated":"2023-07-23T10:58:54Z","status":"ok"}