{"id":14321,"org_id":17717,"name":"Korbitec","aka":"LexisNexis","name_long":"","website":"http://www.lexisnexis.co.za","social_media":[{"service":"website","identifier":"http://www.lexisnexis.co.za"}],"asn":328156,"looking_glass":"","route_server":"","irr_as_set":"","info_type":"Enterprise","info_types":["Enterprise"],"info_prefixes4":1,"info_prefixes6":1,"info_traffic":"","info_ratio":"Balanced","info_scope":"Africa","info_unicast":true,"info_multicast":false,"info_ipv6":true,"info_never_via_route_servers":false,"ix_count":2,"fac_count":2,"notes":"","netixlan_updated":"2021-09-22T00:07:46Z","netfac_updated":"2017-08-25T10:52:57Z","poc_updated":null,"policy_url":"","policy_general":"Open","policy_locations":"Not Required","policy_ratio":false,"policy_contracts":"Not Required","allow_ixp_update":false,"status_dashboard":null,"rir_status":"ok","rir_status_updated":"2024-06-26T04:47:55Z","logo":null,"created":"2017-08-11T11:28:07Z","updated":"2022-07-27T05:37:00Z","status":"ok"}