{"id":32655,"org_id":34897,"name":"Pronto Broadband Solutions","aka":"","name_long":"","website":"http://www.prontobroadband.com","social_media":[{"service":"website","identifier":"http://www.prontobroadband.com"}],"asn":329230,"looking_glass":"","route_server":"","irr_as_set":"AS329230:AS-ALL","info_type":"Cable/DSL/ISP","info_types":["Cable/DSL/ISP"],"info_prefixes4":4,"info_prefixes6":0,"info_traffic":"","info_ratio":"Not Disclosed","info_scope":"Not Disclosed","info_unicast":false,"info_multicast":false,"info_ipv6":false,"info_never_via_route_servers":false,"ix_count":2,"fac_count":2,"notes":"","netixlan_updated":"2024-03-22T10:07:28Z","netfac_updated":"2023-11-02T10:55:17Z","poc_updated":"2023-11-02T09:51:29Z","policy_url":"","policy_general":"Open","policy_locations":"Not Required","policy_ratio":false,"policy_contracts":"Not Required","allow_ixp_update":false,"status_dashboard":"","rir_status":"ok","rir_status_updated":"2024-06-26T04:47:55Z","logo":null,"created":"2023-03-27T20:28:49Z","updated":"2024-03-22T10:08:14Z","status":"ok"}