{"id":31114,"org_id":16296,"name":"Sky Digital Co.,  AS38042","aka":"","name_long":"","website":"https://transit.tw","social_media":[{"service":"website","identifier":"https://transit.tw"}],"asn":38042,"looking_glass":"","route_server":"","irr_as_set":"AS-IMCLOUD","info_type":"Cable/DSL/ISP","info_types":["Cable/DSL/ISP"],"info_prefixes4":1000,"info_prefixes6":100,"info_traffic":"","info_ratio":"Not Disclosed","info_scope":"Not Disclosed","info_unicast":false,"info_multicast":false,"info_ipv6":false,"info_never_via_route_servers":false,"ix_count":0,"fac_count":1,"notes":"","netixlan_updated":"2022-11-09T03:06:55Z","netfac_updated":"2025-03-01T12:40:12Z","poc_updated":"2022-09-30T12:40:42Z","policy_url":"","policy_general":"Open","policy_locations":"Not Required","policy_ratio":false,"policy_contracts":"Not Required","allow_ixp_update":false,"status_dashboard":"","rir_status":"ok","rir_status_updated":"2024-06-26T04:47:55Z","logo":null,"created":"2022-09-29T16:50:21Z","updated":"2025-03-01T12:40:24Z","status":"ok"}