{"id":14374,"org_id":6034,"name":"Blue Jeans Network, Inc. - US East","aka":"","name_long":"","website":"https://www.bluejeans.com","social_media":[{"service":"website","identifier":"https://www.bluejeans.com"}],"asn":393490,"looking_glass":"","route_server":"","irr_as_set":"AS-BJN-DC","info_type":"","info_types":[],"info_prefixes4":1,"info_prefixes6":0,"info_traffic":"5-10Gbps","info_ratio":"Balanced","info_scope":"North America","info_unicast":true,"info_multicast":false,"info_ipv6":false,"info_never_via_route_servers":false,"ix_count":1,"fac_count":1,"notes":"","netixlan_updated":"2020-04-14T19:29:15Z","netfac_updated":"2020-01-22T04:21:53Z","poc_updated":"2020-04-14T19:31:47Z","policy_url":"","policy_general":"Selective","policy_locations":"Not Required","policy_ratio":false,"policy_contracts":"Not Required","allow_ixp_update":false,"status_dashboard":null,"rir_status":"ok","rir_status_updated":"2024-06-26T04:47:55Z","logo":null,"created":"2017-08-14T23:49:07Z","updated":"2022-07-27T05:37:05Z","status":"ok"}