{"id":18152,"org_id":21280,"name":"Wellesley Municipal Light Plant","aka":"","name_long":"","website":"https://wellesleyma.gov/228/Municipal-Light-Plant","social_media":[{"service":"website","identifier":"https://wellesleyma.gov/228/Municipal-Light-Plant"}],"asn":397116,"looking_glass":"","route_server":"","irr_as_set":"","info_type":"Cable/DSL/ISP","info_types":["Cable/DSL/ISP"],"info_prefixes4":5,"info_prefixes6":1,"info_traffic":"","info_ratio":"Heavy Inbound","info_scope":"Regional","info_unicast":true,"info_multicast":false,"info_ipv6":false,"info_never_via_route_servers":false,"ix_count":1,"fac_count":2,"notes":"","netixlan_updated":"2018-10-26T18:39:05Z","netfac_updated":"2026-01-02T02:52:47Z","poc_updated":null,"policy_url":"","policy_general":"Selective","policy_locations":"Not Required","policy_ratio":false,"policy_contracts":"Not Required","allow_ixp_update":false,"status_dashboard":"","rir_status":"ok","rir_status_updated":"2024-06-26T04:47:55Z","logo":null,"created":"2018-10-26T18:00:52Z","updated":"2026-01-02T02:53:26Z","status":"ok"}