{"id":15568,"org_id":18845,"name":"METROLINE","aka":"","name_long":"","website":"http://www.metroline.pl","social_media":[{"service":"website","identifier":"http://www.metroline.pl"}],"asn":44655,"looking_glass":"","route_server":"","irr_as_set":"AS-METROLINE","info_type":"Cable/DSL/ISP","info_types":["Cable/DSL/ISP"],"info_prefixes4":1000,"info_prefixes6":500,"info_traffic":"","info_ratio":"Balanced","info_scope":"Regional","info_unicast":true,"info_multicast":true,"info_ipv6":true,"info_never_via_route_servers":false,"ix_count":3,"fac_count":3,"notes":"","netixlan_updated":"2025-04-25T19:59:11Z","netfac_updated":"2023-04-08T20:08:22Z","poc_updated":"2020-12-20T12:34:06Z","policy_url":"","policy_general":"Open","policy_locations":"Not Required","policy_ratio":false,"policy_contracts":"Not Required","allow_ixp_update":false,"status_dashboard":"","rir_status":"ok","rir_status_updated":"2024-06-26T04:47:55Z","logo":null,"created":"2017-12-24T23:54:39Z","updated":"2025-04-25T19:59:26Z","status":"ok"}