{"id":4253,"org_id":5084,"name":"Net Onboard Sdn Bhd","aka":"NET","name_long":"","website":"https://www.netonboard.com","social_media":[{"service":"website","identifier":"https://www.netonboard.com"}],"asn":45144,"looking_glass":"","route_server":"","irr_as_set":"","info_type":"Content","info_types":["Content"],"info_prefixes4":30,"info_prefixes6":1,"info_traffic":"100-1000Mbps","info_ratio":"Mostly Outbound","info_scope":"Asia Pacific","info_unicast":true,"info_multicast":false,"info_ipv6":false,"info_never_via_route_servers":false,"ix_count":1,"fac_count":1,"notes":"Software Development & Hosting Services","netixlan_updated":"2020-08-12T08:15:17Z","netfac_updated":"2016-03-14T21:12:55Z","poc_updated":"2020-08-14T07:47:34Z","policy_url":"","policy_general":"Open","policy_locations":"Not Required","policy_ratio":false,"policy_contracts":"Not Required","allow_ixp_update":false,"status_dashboard":null,"rir_status":"ok","rir_status_updated":"2024-06-26T04:47:55Z","logo":null,"created":"2011-09-20T04:09:09Z","updated":"2022-07-27T05:34:31Z","status":"ok"}