{"id":19968,"org_id":23008,"name":"Winnebago Cooperative Telecom Association","aka":"WCTA","name_long":"Winnebago Cooperative Telecom Association","website":"http://www.wctatel.net","social_media":[{"service":"website","identifier":"http://www.wctatel.net"}],"asn":46892,"looking_glass":"","route_server":"","irr_as_set":"ARIN::AS-WINNE-1","info_type":"Cable/DSL/ISP","info_types":["Cable/DSL/ISP"],"info_prefixes4":100,"info_prefixes6":1,"info_traffic":"20-50Gbps","info_ratio":"Mostly Inbound","info_scope":"North America","info_unicast":true,"info_multicast":false,"info_ipv6":true,"info_never_via_route_servers":false,"ix_count":1,"fac_count":2,"notes":"","netixlan_updated":"2024-03-27T18:58:25Z","netfac_updated":"2019-12-18T17:20:32Z","poc_updated":"2022-07-29T16:01:44Z","policy_url":"","policy_general":"Open","policy_locations":"Not Required","policy_ratio":false,"policy_contracts":"Not Required","allow_ixp_update":false,"status_dashboard":"","rir_status":"ok","rir_status_updated":"2024-06-26T04:47:55Z","logo":null,"created":"2019-06-03T15:17:15Z","updated":"2024-03-27T20:20:48Z","status":"ok"}