{"id":9949,"org_id":13917,"name":"iBrowse SARL","aka":"","name_long":"","website":"http://www.ibrowse.com","social_media":[{"service":"website","identifier":"http://www.ibrowse.com"}],"asn":47866,"looking_glass":"","route_server":"","irr_as_set":"AS47866","info_type":"Cable/DSL/ISP","info_types":["Cable/DSL/ISP"],"info_prefixes4":20,"info_prefixes6":10,"info_traffic":"1-5Gbps","info_ratio":"Heavy Inbound","info_scope":"Europe","info_unicast":true,"info_multicast":false,"info_ipv6":true,"info_never_via_route_servers":false,"ix_count":2,"fac_count":10,"notes":"iBrowse builds and manages international private WANs for large multinational companies with decentralized sites and needs for high quality communications in multiple countries over a resilient, redundant MPLS network. Our solution includes sophisticated QoS and application-aware load balancing, as well as a single security policy across a single European network. We also provide value-added services such as guest WiFi access. iBrowse operates its own MPLS network connecting its core sites in data centres in the UK, France, Germany, Italy and Spain.","netixlan_updated":"2025-11-20T13:39:27Z","netfac_updated":"2017-03-17T15:03:49Z","poc_updated":"2020-10-15T09:25:11Z","policy_url":"","policy_general":"Selective","policy_locations":"Preferred","policy_ratio":false,"policy_contracts":"Not Required","allow_ixp_update":false,"status_dashboard":null,"rir_status":"ok","rir_status_updated":"2024-06-26T04:47:55Z","logo":null,"created":"2016-04-05T16:40:11Z","updated":"2022-07-27T05:34:34Z","status":"ok"}