{"id":18349,"org_id":21469,"name":"HELP INTERNET","aka":"","name_long":"","website":"http://www.helpinternet.com.br","social_media":[{"service":"website","identifier":"http://www.helpinternet.com.br"}],"asn":52742,"looking_glass":"","route_server":"","irr_as_set":"AS52742:AS-HELP_INTERNET","info_type":"Cable/DSL/ISP","info_types":["Cable/DSL/ISP"],"info_prefixes4":100,"info_prefixes6":15,"info_traffic":"20-50Gbps","info_ratio":"Mostly Inbound","info_scope":"Regional","info_unicast":true,"info_multicast":false,"info_ipv6":true,"info_never_via_route_servers":false,"ix_count":1,"fac_count":1,"notes":"","netixlan_updated":"2024-11-11T18:44:32Z","netfac_updated":"2024-11-11T18:05:32Z","poc_updated":"2020-12-03T14:17:02Z","policy_url":"","policy_general":"Selective","policy_locations":"Not Required","policy_ratio":false,"policy_contracts":"Not Required","allow_ixp_update":false,"status_dashboard":"","rir_status":"ok","rir_status_updated":"2024-06-26T04:47:55Z","logo":null,"created":"2018-11-16T07:37:06Z","updated":"2024-11-11T18:44:42Z","status":"ok"}