{"id":5310,"org_id":7417,"name":"1 Telecom Servicos de Internet","aka":"UM TELECOM","name_long":"1TELECOM SERVICOS DE TECNOLOGIA EM INTERNET LTDA","website":"https://umtelecom.com.br/","social_media":[{"service":"website","identifier":"https://umtelecom.com.br/"}],"asn":52965,"looking_glass":"","route_server":"","irr_as_set":"RADB::AS-1TELECOM-CUSTOMERS01","info_type":"NSP","info_types":["NSP"],"info_prefixes4":2000,"info_prefixes6":1000,"info_traffic":"500-1000Gbps","info_ratio":"Mostly Inbound","info_scope":"South America","info_unicast":true,"info_multicast":false,"info_ipv6":true,"info_never_via_route_servers":false,"ix_count":6,"fac_count":12,"notes":"","netixlan_updated":"2025-11-24T18:42:03Z","netfac_updated":"2025-10-12T19:18:43Z","poc_updated":"2025-12-15T21:13:28Z","policy_url":"","policy_general":"Open","policy_locations":"Preferred","policy_ratio":true,"policy_contracts":"Required","allow_ixp_update":false,"status_dashboard":"","rir_status":"ok","rir_status_updated":"2024-06-26T04:47:55Z","logo":"http://testserver/m/logos_user_supplied/network-5310-b18d524e.jpg","created":"2013-02-18T11:36:20Z","updated":"2025-10-14T21:42:17Z","status":"ok"}