{"id":6929,"org_id":9492,"name":"Arista SD-WAN","aka":"VeloCloud SD-WAN","name_long":"","website":"https://www.arista.com","social_media":[{"service":"website","identifier":"https://www.arista.com"}],"asn":53766,"looking_glass":"","route_server":"","irr_as_set":"RADB::AS-VMWARE-SASE","info_type":"NSP","info_types":["NSP"],"info_prefixes4":500,"info_prefixes6":200,"info_traffic":"","info_ratio":"Mostly Outbound","info_scope":"Global","info_unicast":true,"info_multicast":false,"info_ipv6":true,"info_never_via_route_servers":false,"ix_count":23,"fac_count":29,"notes":"","netixlan_updated":"2025-11-24T20:40:17Z","netfac_updated":"2025-05-21T12:59:24Z","poc_updated":"2025-07-01T17:18:59Z","policy_url":"","policy_general":"Selective","policy_locations":"Preferred","policy_ratio":false,"policy_contracts":"Not Required","allow_ixp_update":false,"status_dashboard":"","rir_status":"ok","rir_status_updated":"2024-06-26T04:47:55Z","logo":null,"created":"2014-06-26T13:04:43Z","updated":"2025-11-21T13:33:29Z","status":"ok"}