{"id":24901,"org_id":27608,"name":"Marco Bungalski","aka":"T-M-Net.de","name_long":"","website":"https://www.t-m-net.de","social_media":[{"service":"website","identifier":"https://www.t-m-net.de"}],"asn":59790,"looking_glass":"","route_server":"","irr_as_set":"AS-BUNGALSKI","info_type":"Cable/DSL/ISP","info_types":["Cable/DSL/ISP","Enterprise"],"info_prefixes4":100,"info_prefixes6":20,"info_traffic":"","info_ratio":"Mostly Inbound","info_scope":"Regional","info_unicast":true,"info_multicast":false,"info_ipv6":true,"info_never_via_route_servers":false,"ix_count":6,"fac_count":8,"notes":"","netixlan_updated":"2026-02-12T13:30:33Z","netfac_updated":"2025-08-28T20:30:25Z","poc_updated":"2020-10-15T23:36:58Z","policy_url":"","policy_general":"Open","policy_locations":"Not Required","policy_ratio":false,"policy_contracts":"Not Required","allow_ixp_update":false,"status_dashboard":"","rir_status":"ok","rir_status_updated":"2024-06-26T04:47:55Z","logo":null,"created":"2020-10-15T22:10:29Z","updated":"2026-02-12T13:30:38Z","status":"ok"}