{"id":12953,"org_id":16536,"name":"Entel S.A. - EntelNet","aka":"ENTEL BOLIVIA","name_long":"","website":"https://www.entel.bo/","social_media":[{"service":"website","identifier":"https://www.entel.bo/"}],"asn":6568,"looking_glass":"","route_server":"","irr_as_set":"AS6568:AS-PROVIDERS AS6568:AS-CLIENTS AS-ENTEL-BOLIVIA","info_type":"","info_types":[],"info_prefixes4":700,"info_prefixes6":500,"info_traffic":"1-5Tbps","info_ratio":"","info_scope":"","info_unicast":true,"info_multicast":true,"info_ipv6":true,"info_never_via_route_servers":false,"ix_count":3,"fac_count":3,"notes":"","netixlan_updated":"2025-10-06T13:54:04Z","netfac_updated":"2025-04-07T19:01:00Z","poc_updated":"2025-04-03T19:42:36Z","policy_url":"https://www.entel.bo","policy_general":"Selective","policy_locations":"Not Required","policy_ratio":true,"policy_contracts":"Private Only","allow_ixp_update":false,"status_dashboard":"","rir_status":"ok","rir_status_updated":"2024-06-26T04:47:55Z","logo":null,"created":"2017-03-24T19:55:25Z","updated":"2025-10-06T13:56:27Z","status":"ok"}