{"id":4463,"org_id":8267,"name":"IRANET","aka":"IPM , IRANET","name_long":"","website":"http://www.iranet.ir","social_media":[{"service":"website","identifier":"http://www.iranet.ir"}],"asn":6736,"looking_glass":"http://lg.iranet.ir","route_server":"","irr_as_set":"RIPE::AS-IRANET-IPM RIPE::AS-IRANET-IPM-V6","info_type":"NSP","info_types":["NSP"],"info_prefixes4":600,"info_prefixes6":30,"info_traffic":"20-50Gbps","info_ratio":"Balanced","info_scope":"Middle East","info_unicast":true,"info_multicast":false,"info_ipv6":true,"info_never_via_route_servers":false,"ix_count":1,"fac_count":1,"notes":"IRANET was founded in 1993 in order to develop and provide the requirements of IPM's scientists","netixlan_updated":"2022-11-09T03:14:19Z","netfac_updated":"2022-11-09T03:15:22Z","poc_updated":"2022-11-09T03:12:50Z","policy_url":"http://www.iranet.ir","policy_general":"Selective","policy_locations":"Not Required","policy_ratio":false,"policy_contracts":"Required","allow_ixp_update":false,"status_dashboard":"","rir_status":"ok","rir_status_updated":"2024-06-26T04:47:55Z","logo":null,"created":"2011-12-18T06:32:40Z","updated":"2022-11-09T22:55:32Z","status":"ok"}