{"id":13027,"org_id":16604,"name":"Independents Fiber Network","aka":"IFN/Bright.net","name_long":"","website":"https://cniteam.com/","social_media":[{"service":"website","identifier":"https://cniteam.com/"}],"asn":7106,"looking_glass":"","route_server":"","irr_as_set":"AS-7106","info_type":"NSP","info_types":["NSP"],"info_prefixes4":134,"info_prefixes6":5,"info_traffic":"100-200Gbps","info_ratio":"Mostly Inbound","info_scope":"Regional","info_unicast":true,"info_multicast":false,"info_ipv6":true,"info_never_via_route_servers":false,"ix_count":1,"fac_count":3,"notes":"","netixlan_updated":"2026-02-27T18:22:13Z","netfac_updated":"2017-04-21T13:01:15Z","poc_updated":"2017-04-21T13:03:59Z","policy_url":"","policy_general":"Selective","policy_locations":"Not Required","policy_ratio":false,"policy_contracts":"Private Only","allow_ixp_update":false,"status_dashboard":"","rir_status":"ok","rir_status_updated":"2024-06-26T04:47:55Z","logo":null,"created":"2017-03-31T15:22:30Z","updated":"2025-11-20T16:35:45Z","status":"ok"}