{"id":17239,"org_id":20425,"name":"HARENET","aka":"HARENET","name_long":"","website":"http://www.harenet.ad.jp","social_media":[{"service":"website","identifier":"http://www.harenet.ad.jp"}],"asn":7664,"looking_glass":"","route_server":"","irr_as_set":"AS-HARENET","info_type":"Cable/DSL/ISP","info_types":["Cable/DSL/ISP"],"info_prefixes4":0,"info_prefixes6":0,"info_traffic":"","info_ratio":"Not Disclosed","info_scope":"Not Disclosed","info_unicast":true,"info_multicast":false,"info_ipv6":true,"info_never_via_route_servers":false,"ix_count":1,"fac_count":0,"notes":"","netixlan_updated":"2020-07-07T00:46:58Z","netfac_updated":null,"poc_updated":"2020-01-22T04:24:17Z","policy_url":"","policy_general":"Open","policy_locations":"Not Required","policy_ratio":false,"policy_contracts":"Not Required","allow_ixp_update":false,"status_dashboard":"","rir_status":"ok","rir_status_updated":"2024-06-26T04:47:55Z","logo":null,"created":"2018-07-09T02:49:16Z","updated":"2024-05-13T08:50:32Z","status":"ok"}