{"id":1297,"org_id":1451,"name":"Nasstar","aka":"GCI Com, Edge Telecom Ltd, Edge Telecommunications Ltd, IP Infrastructures Ltd, Invomo Ltd,NetServices UK Ltd, Outsourcery Hosting and Fusion Media Networks","name_long":"","website":"https://www.nasstar.com","social_media":[{"service":"website","identifier":"https://www.nasstar.com"}],"asn":8851,"looking_glass":"","route_server":"","irr_as_set":"AS-GCICOM","info_type":"Cable/DSL/ISP","info_types":["Cable/DSL/ISP"],"info_prefixes4":1000,"info_prefixes6":10,"info_traffic":"50-100Gbps","info_ratio":"Mostly Inbound","info_scope":"Regional","info_unicast":true,"info_multicast":false,"info_ipv6":true,"info_never_via_route_servers":false,"ix_count":3,"fac_count":7,"notes":"Nasstar is a trading name of the GCI Telecom Group.","netixlan_updated":"2024-08-16T13:52:27Z","netfac_updated":"2024-06-29T13:28:42Z","poc_updated":"2025-02-01T18:04:40Z","policy_url":"","policy_general":"Open","policy_locations":"Not Required","policy_ratio":false,"policy_contracts":"Not Required","allow_ixp_update":false,"status_dashboard":"","rir_status":"ok","rir_status_updated":"2024-06-26T04:47:55Z","logo":null,"created":"2007-09-06T16:06:08Z","updated":"2024-03-01T12:05:33Z","status":"ok"}